psycopg_pool/__init__.py
psycopg_pool/_acompat.py
psycopg_pool/_compat.py
psycopg_pool/_task.py
psycopg_pool/abc.py
psycopg_pool/base.py
psycopg_pool/base_null_pool.py
psycopg_pool/errors.py
psycopg_pool/null_pool.py
psycopg_pool/null_pool_async.py
psycopg_pool/pool.py
psycopg_pool/pool_async.py
psycopg_pool/py.typed
psycopg_pool/sched.py
psycopg_pool/sched_async.py
psycopg_pool/version.py
psycopg_pool-3.2.2.dist-info/LICENSE.txt
psycopg_pool-3.2.2.dist-info/METADATA
psycopg_pool-3.2.2.dist-info/WHEEL
psycopg_pool-3.2.2.dist-info/top_level.txt
psycopg_pool-3.2.2.dist-info/RECORD
